task3/ram2ports.sv
module ram2ports    #(
    parameter       ADDRESS_WIDTH = 8,
                    DATA_WIDTH = 8
)(
    input logic                         clk,
    input logic                         wr,
    input logic                         rd,
    input logic     [ADDRESS_WIDTH-1:0] wr_addr,
    input logic     [ADDRESS_WIDTH-1:0] rd_addr,
    input logic     [DATA_WIDTH-1:0]    din,
    output logic    [DATA_WIDTH-1:0]    dout
);

logic   [DATA_WIDTH-1:0] ram_array [2**ADDRESS_WIDTH-1:0];

always_ff @ (posedge clk) begin
    $display(din);
    
    if (wr == 1'b1)
        ram_array[wr_addr] <= din;
    if (rd == 1'b1)
        //output is synchronous
        dout <= ram_array[rd_addr];
end
endmodule

task3/counter.sv
module counter #(
    parameter WIDTH = 8
)(
    //interface signals 
    input logic             clk,        //clock
    input logic             rst,        //reset
    output logic [WIDTH:0] count      //count ouput
);

always_ff @ (posedge clk) begin
    //$display(count);
    if(rst) count <= {(WIDTH){1'b0}};
    else    count <= count + {{WIDTH-1{1'b0}}, 1'b1};
end
endmodule

task3/sigdelay.sv
module sigdelay  #(
    parameter   WIDTH = 8,
                ADDRESS_WIDTH = 9
)(
    //interface signals
    input logic                 clk,
    input logic                 rst,
    input logic [ADDRESS_WIDTH-1:0]     offset, //offset between read and write of RAM
    input logic                 wr, //write into ram enable
    input logic                 rd,
    input logic [WIDTH-1:0]     mic_signal,
    output logic [WIDTH-1:0]    delayed_signal
);

    logic [ADDRESS_WIDTH-1:0]             wire1;
    logic [ADDRESS_WIDTH-1:0]             wire2;

always_ff @ (posedge clk)
    wire2 <= wire1+offset;

counter #(9) myCounter (
    .clk(clk),
    .rst(rst),
    .count(wire1)
);

ram2ports #(9,8) myRam (
    .clk(clk),
    .wr(wr),
    .rd(rd),
    .wr_addr(wire1),
    .rd_addr(wire2),
    .din(mic_signal),
    .dout(delayed_signal)
);
endmodule

task3/sigdelay.vcd
$version Generated by VerilatedVcd $end
$timescale 1ps $end

 $scope module TOP $end
  $var wire  1 & clk $end
  $var wire  8 , delayed_signal [7:0] $end
  $var wire  8 + mic_signal [7:0] $end
  $var wire  9 ( offset [8:0] $end
  $var wire  1 * rd $end
  $var wire  1 ' rst $end
  $var wire  1 ) wr $end
  $scope module sigdelay $end
   $var wire 32 . ADDRESS_WIDTH [31:0] $end
   $var wire 32 - WIDTH [31:0] $end
   $var wire  1 & clk $end
   $var wire  8 , delayed_signal [7:0] $end
   $var wire  8 + mic_signal [7:0] $end
   $var wire  9 ( offset [8:0] $end
   $var wire  1 * rd $end
   $var wire  1 ' rst $end
   $var wire  9 # wire1 [8:0] $end
   $var wire  9 $ wire2 [8:0] $end
   $var wire  1 ) wr $end
   $scope module myCounter $end
    $var wire 32 . WIDTH [31:0] $end
    $var wire  1 & clk $end
    $var wire 10 % count [9:0] $end
    $var wire  1 ' rst $end
   $upscope $end
   $scope module myRam $end
    $var wire 32 . ADDRESS_WIDTH [31:0] $end
    $var wire 32 - DATA_WIDTH [31:0] $end
    $var wire  1 & clk $end
    $var wire  8 + din [7:0] $end
    $var wire  8 , dout [7:0] $end
    $var wire  1 * rd $end
    $var wire  9 $ rd_addr [8:0] $end
    $var wire  1 ) wr $end
    $var wire  9 # wr_addr [8:0] $end
   $upscope $end
  $upscope $end
 $upscope $end
$enddefinitions $end


#0
b000000000 #
b000000000 $
b0000000000 %
1&
0'
b001000000 (
1)
1*
b00000000 +
b00000000 ,
b00000000000000000000000000001000 -
b00000000000000000000000000001001 .
#1
0&
#2
b000000001 #
b001000000 $
b0000000001 %
1&
b000000000 (
b01101001 +
#3
0&
#4
b000000010 #
b000000001 $
b0000000010 %
1&
b01011010 +
#5
0&
#6
b000000011 #
b000000010 $
b0000000011 %
1&
b01010111 +
b01101001 ,
#7
0&
#8
b000000100 #
b000000011 $
b0000000100 %
1&
b01011101 +
b01011010 ,
#9
0&
#10
b000000101 #
b000000100 $
b0000000101 %
1&
b01100111 +
b01010111 ,
#11
0&
#12
b000000110 #
b000000101 $
b0000000110 %
1&
b01110111 +
b01011101 ,
#13
0&
#14
b000000111 #
b000000110 $
b0000000111 %
1&
b10000010 +
b01100111 ,
#15
0&
#16
b000001000 #
b000000111 $
b0000001000 %
1&
b10000100 +
b01110111 ,
#17
0&
#18
b000001001 #
b000001000 $
b0000001001 %
1&
b01111001 +
b10000010 ,
#19
0&
#20
b000001010 #
b000001001 $
b0000001010 %
1&
b01101111 +
b10000100 ,
#21
0&
#22
b000001011 #
b000001010 $
b0000001011 %
1&
b01100011 +
b01111001 ,
#23
0&
#24
b000001100 #
b000001011 $
b0000001100 %
1&
b01010101 +
b01101111 ,
#25
0&
#26
b000001101 #
b000001100 $
b0000001101 %
1&
b01011000 +
b01100011 ,
#27
0&
#28
b000001110 #
b000001101 $
b0000001110 %
1&
b01100000 +
b01010101 ,
#29
0&
#30
b000001111 #
b000001110 $
b0000001111 %
1&
b01101110 +
b01011000 ,
#31
0&
#32
b000010000 #
b000001111 $
b0000010000 %
1&
b01111011 +
b01100000 ,
#33
0&
#34
b000010001 #
b000010000 $
b0000010001 %
1&
b10000001 +
b01101110 ,
#35
0&
#36
b000010010 #
b000010001 $
b0000010010 %
1&
b10000000 +
b01111011 ,
#37
0&
#38
b000010011 #
b000010010 $
b0000010011 %
1&
b01110100 +
b10000001 ,
#39
0&
#40
b000010100 #
b000010011 $
b0000010100 %
1&
b01100101 +
b10000000 ,
#41
0&
#42
b000010101 #
b000010100 $
b0000010101 %
1&
b01011000 +
b01110100 ,
#43
0&
#44
b000010110 #
b000010101 $
b0000010110 %
1&
b01010101 +
b01100101 ,
#45
0&
#46
b000010111 #
b000010110 $
b0000010111 %
1&
b01011001 +
b01011000 ,
#47
0&
#48
b000011000 #
b000010111 $
b0000011000 %
1&
b01101000 +
b01010101 ,
#49
0&
#50
b000011001 #
b000011000 $
b0000011001 %
1&
b01111000 +
b01011001 ,
#51
0&
#52
b000011010 #
b000011001 $
b0000011010 %
1&
b10000001 +
b01101000 ,
#53
0&
#54
b000011011 #
b000011010 $
b0000011011 %
1&
b10000100 +
b01111000 ,
#55
0&
#56
b000011100 #
b000011011 $
b0000011100 %
1&
b01111110 +
b10000001 ,
#57
0&
#58
b000011101 #
b000011100 $
b0000011101 %
1&
b01110000 +
b10000100 ,
#59
0&
#60
b000011110 #
b000011101 $
b0000011110 %
1&
b01100001 +
b01111110 ,
#61
0&
#62
b000011111 #
b000011110 $
b0000011111 %
1&
b01010110 +
b01110000 ,
#63
0&
#64
b000100000 #
b000011111 $
b0000100000 %
1&
b01100001 ,
#65
0&
#66
b000100001 #
b000100000 $
b0000100001 %
1&
b01011110 +
b01010110 ,
#67
0&
#68
b000100010 #
b000100001 $
b0000100010 %
1&
b01110000 +
#69
0&
#70
b000100011 #
b000100010 $
b0000100011 %
1&
b01111000 +
b01011110 ,
#71
0&
#72
b000100100 #
b000100011 $
b0000100100 %
1&
b10000010 +
b01110000 ,
#73
0&
#74
b000100101 #
b000100100 $
b0000100101 %
1&
b10000000 +
b01111000 ,
#75
0&
#76
b000100110 #
b000100101 $
b0000100110 %
1&
b01111001 +
b10000010 ,
#77
0&
#78
b000100111 #
b000100110 $
b0000100111 %
1&
b01100110 +
b10000000 ,
#79
0&
#80
b000101000 #
b000100111 $
b0000101000 %
1&
b01011010 +
b01111001 ,
#81
0&
#82
b000101001 #
b000101000 $
b0000101001 %
1&
b01010110 +
b01100110 ,
#83
0&
#84
b000101010 #
b000101001 $
b0000101010 %
1&
b01011000 +
b01011010 ,
#85
0&
#86
b000101011 #
b000101010 $
b0000101011 %
1&
b01101000 +
b01010110 ,
#87
0&
#88
b000101100 #
b000101011 $
b0000101100 %
1&
b01110101 +
b01011000 ,
#89
0&
#90
b000101101 #
b000101100 $
b0000101101 %
1&
b10000000 +
b01101000 ,
#91
0&
#92
b000101110 #
b000101101 $
b0000101110 %
1&
b10000100 +
b01110101 ,
#93
0&
#94
b000101111 #
b000101110 $
b0000101111 %
1&
b01111101 +
b10000000 ,
#95
0&
#96
b000110000 #
b000101111 $
b0000110000 %
1&
b01110000 +
b10000100 ,
#97
0&
#98
b000110001 #
b000110000 $
b0000110001 %
1&
b01011101 +
b01111101 ,
#99
0&
#100
b000110010 #
b000110001 $
b0000110010 %
1&
b01010101 +
b01110000 ,
#101
0&
#102
b000110011 #
b000110010 $
b0000110011 %
1&
b01010110 +
b01011101 ,
#103
0&
#104
b000110100 #
b000110011 $
b0000110100 %
1&
b01011111 +
b01010101 ,
#105
0&
#106
b000110101 #
b000110100 $
b0000110101 %
1&
b01101100 +
b01010110 ,
#107
0&
#108
b000110110 #
b000110101 $
b0000110110 %
1&
b01111010 +
b01011111 ,
#109
0&
#110
b000110111 #
b000110110 $
b0000110111 %
1&
b10000011 +
b01101100 ,
#111
0&
#112
b000111000 #
b000110111 $
b0000111000 %
1&
b10000010 +
b01111010 ,
#113
0&
#114
b000111001 #
b000111000 $
b0000111001 %
1&
b01110110 +
b10000011 ,
#115
0&
#116
b000111010 #
b000111001 $
b0000111010 %
1&
b01101010 +
b10000010 ,
#117
0&
#118
b000111011 #
b000111010 $
b0000111011 %
1&
b01011101 +
b01110110 ,
#119
0&
#120
b000111100 #
b000111011 $
b0000111100 %
1&
b01010111 +
b01101010 ,
#121
0&
#122
b000111101 #
b000111100 $
b0000111101 %
1&
b01011001 +
b01011101 ,
#123
0&
#124
b000111110 #
b000111101 $
b0000111110 %
1&
b01100111 +
b01010111 ,
#125
0&
#126
b000111111 #
b000111110 $
b0000111111 %
1&
b01110101 +
b01011001 ,
#127
0&
#128
b001000000 #
b000111111 $
b0001000000 %
1&
b10000100 +
b01100111 ,
#129
0&
#130
b001000001 #
b001000000 $
b0001000001 %
1&
b10000001 +
b01110101 ,
#131
0&
#132
b001000010 #
b001000001 $
b0001000010 %
1&
b01111100 +
b10000100 ,
#133
0&
#134
b001000011 #
b001000010 $
b0001000011 %
1&
b01110010 +
b10000001 ,
#135
0&
#136
b001000100 #
b001000011 $
b0001000100 %
1&
b01100010 +
b01111100 ,
#137
0&
#138
b001000101 #
b001000100 $
b0001000101 %
1&
b01010110 +
b01110010 ,
#139
0&
#140
b001000110 #
b001000101 $
b0001000110 %
1&
b01010100 +
b01100010 ,
#141
0&
#142
b001000111 #
b001000110 $
b0001000111 %
1&
b01011100 +
b01010110 ,
#143
0&
#144
b001001000 #
b001000111 $
b0001001000 %
1&
b01101010 +
b01010100 ,
#145
0&
#146
b001001001 #
b001001000 $
b0001001001 %
1&
b01111001 +
b01011100 ,
#147
0&
#148
b001001010 #
b001001001 $
b0001001010 %
1&
b10000010 +
b01101010 ,
#149
0&
#150
b001001011 #
b001001010 $
b0001001011 %
1&
b10000000 +
b01111001 ,
#151
0&
#152
b001001100 #
b001001011 $
b0001001100 %
1&
b01111000 +
b10000010 ,
#153
0&
#154
b001001101 #
b001001100 $
b0001001101 %
1&
b01101010 +
b10000000 ,
#155
0&
#156
b001001110 #
b001001101 $
b0001001110 %
1&
b01011110 +
b01111000 ,
#157
0&
#158
b001001111 #
b001001110 $
b0001001111 %
1&
b01011000 +
b01101010 ,
#159
0&
#160
b001010000 #
b001001111 $
b0001010000 %
1&
b01011001 +
b01011110 ,
#161
0&
#162
b001010001 #
b001010000 $
b0001010001 %
1&
b01100110 +
b01011000 ,
#163
0&
#164
b001010010 #
b001010001 $
b0001010010 %
1&
b01110100 +
b01011001 ,
#165
0&
#166
b001010011 #
b001010010 $
b0001010011 %
1&
b10000000 +
b01100110 ,
#167
0&
#168
b001010100 #
b001010011 $
b0001010100 %
1&
b10000010 +
b01110100 ,
#169
0&
#170
b001010101 #
b001010100 $
b0001010101 %
1&
b01111111 +
b10000000 ,
#171
0&
#172
b001010110 #
b001010101 $
b0001010110 %
1&
b01110010 +
b10000010 ,
#173
0&
#174
b001010111 #
b001010110 $
b0001010111 %
1&
b01100010 +
b01111111 ,
#175
0&
#176
b001011000 #
b001010111 $
b0001011000 %
1&
b01011000 +
b01110010 ,
#177
0&
#178
b001011001 #
b001011000 $
b0001011001 %
1&
b01010101 +
b01100010 ,
#179
0&
#180
b001011010 #
b001011001 $
b0001011010 %
1&
b01011010 +
b01011000 ,
#181
0&
#182
b001011011 #
b001011010 $
b0001011011 %
1&
b01101100 +
b01010101 ,
#183
0&
#184
b001011100 #
b001011011 $
b0001011100 %
1&
b01111010 +
b01011010 ,
#185
0&
#186
b001011101 #
b001011100 $
b0001011101 %
1&
b10000100 +
b01101100 ,
#187
0&
#188
b001011110 #
b001011101 $
b0001011110 %
1&
b10000011 +
b01111010 ,
#189
0&
#190
b001011111 #
b001011110 $
b0001011111 %
1&
b01111001 +
b10000100 ,
#191
0&
#192
b001100000 #
b001011111 $
b0001100000 %
1&
b01101010 +
b10000011 ,
#193
0&
#194
b001100001 #
b001100000 $
b0001100001 %
1&
b01111100 +
b01111001 ,
#195
0&
#196
b001100010 #
b001100001 $
b0001100010 %
1&
b10000100 +
b01101010 ,
#197
0&
#198
b001100011 #
b001100010 $
b0001100011 %
1&
b01111100 +
b01111100 ,
#199
0&
#200
b001100100 #
b001100011 $
b0001100100 %
1&
b01101100 +
b10000100 ,
#201
0&
#202
b001100101 #
b001100100 $
b0001100101 %
1&
b01011110 +
b01111100 ,
#203
0&
#204
b001100110 #
b001100101 $
b0001100110 %
1&
b01010110 +
b01101100 ,
#205
0&
#206
b001100111 #
b001100110 $
b0001100111 %
1&
b01010111 +
b01011110 ,
#207
0&
#208
b001101000 #
b001100111 $
b0001101000 %
1&
b01100000 +
b01010110 ,
#209
0&
#210
b001101001 #
b001101000 $
b0001101001 %
1&
b01110011 +
b01010111 ,
#211
0&
#212
b001101010 #
b001101001 $
b0001101010 %
1&
b01111100 +
b01100000 ,
#213
0&
#214
b001101011 #
b001101010 $
b0001101011 %
1&
b10000101 +
b01110011 ,
#215
0&
#216
b001101100 #
b001101011 $
b0001101100 %
1&
b10000001 +
b01111100 ,
#217
0&
#218
b001101101 #
b001101100 $
b0001101101 %
1&
b01111001 +
b10000101 ,
#219
0&
#220
b001101110 #
b001101101 $
b0001101110 %
1&
b01101011 +
b10000001 ,
#221
0&
#222
b001101111 #
b001101110 $
b0001101111 %
1&
b01011011 +
b01111001 ,
#223
0&
#224
b001110000 #
b001101111 $
b0001110000 %
1&
b01010101 +
b01101011 ,
#225
0&
#226
b001110001 #
b001110000 $
b0001110001 %
1&
b01011001 +
b01011011 ,
#227
0&
#228
b001110010 #
b001110001 $
b0001110010 %
1&
b01100101 +
b01010101 ,
#229
0&
#230
b001110011 #
b001110010 $
b0001110011 %
1&
b01110100 +
b01011001 ,
#231
0&
#232
b001110100 #
b001110011 $
b0001110100 %
1&
b01111100 +
b01100101 ,
#233
0&
#234
b001110101 #
b001110100 $
b0001110101 %
1&
b10000000 +
b01110100 ,
#235
0&
#236
b001110110 #
b001110101 $
b0001110110 %
1&
b01111101 +
b01111100 ,
#237
0&
#238
b001110111 #
b001110110 $
b0001110111 %
1&
b01110001 +
b10000000 ,
#239
0&
#240
b001111000 #
b001110111 $
b0001111000 %
1&
b01100010 +
b01111101 ,
#241
0&
#242
b001111001 #
b001111000 $
b0001111001 %
1&
b01010111 +
b01110001 ,
#243
0&
#244
b001111010 #
b001111001 $
b0001111010 %
1&
b01010100 +
b01100010 ,
#245
0&
#246
b001111011 #
b001111010 $
b0001111011 %
1&
b01011011 +
b01010111 ,
#247
0&
#248
b001111100 #
b001111011 $
b0001111100 %
1&
b01101010 +
b01010100 ,
#249
0&
#250
b001111101 #
b001111100 $
b0001111101 %
1&
b01110111 +
b01011011 ,
#251
0&
#252
b001111110 #
b001111101 $
b0001111110 %
1&
b10000000 +
b01101010 ,
#253
0&
#254
b001111111 #
b001111110 $
b0001111111 %
1&
b10000001 +
b01110111 ,
#255
0&
#256
b010000000 #
b001111111 $
b0010000000 %
1&
b01111000 +
b10000000 ,
#257
0&
#258
b010000001 #
b010000000 $
b0010000001 %
1&
b01101000 +
b10000001 ,
#259
0&
#260
b010000010 #
b010000001 $
b0010000010 %
1&
b01011100 +
b01111000 ,
#261
0&
#262
b010000011 #
b010000010 $
b0010000011 %
1&
b01010101 +
b01101000 ,
#263
0&
#264
b010000100 #
b010000011 $
b0010000100 %
1&
b01011001 +
b01011100 ,
#265
0&
#266
b010000101 #
b010000100 $
b0010000101 %
1&
b01100101 +
b01010101 ,
#267
0&
#268
b010000110 #
b010000101 $
b0010000110 %
1&
b01110010 +
b01011001 ,
#269
0&
#270
b010000111 #
b010000110 $
b0010000111 %
1&
b01111100 +
b01100101 ,
#271
0&
#272
b010001000 #
b010000111 $
b0010001000 %
1&
b10000100 +
b01110010 ,
#273
0&
#274
b010001001 #
b010001000 $
b0010001001 %
1&
b01111101 +
b01111100 ,
#275
0&
#276
b010001010 #
b010001001 $
b0010001010 %
1&
b01110001 +
b10000100 ,
#277
0&
#278
b010001011 #
b010001010 $
b0010001011 %
1&
b01100010 +
b01111101 ,
#279
0&
#280
b010001100 #
b010001011 $
b0010001100 %
1&
b01011000 +
b01110001 ,
#281
0&
#282
b010001101 #
b010001100 $
b0010001101 %
1&
b01010111 +
b01100010 ,
#283
0&
#284
b010001110 #
b010001101 $
b0010001110 %
1&
b01011010 +
b01011000 ,
#285
0&
#286
b010001111 #
b010001110 $
b0010001111 %
1&
b01101001 +
b01010111 ,
#287
0&
#288
b010010000 #
b010001111 $
b0010010000 %
1&
b01111001 +
b01011010 ,
#289
0&
#290
b010010001 #
b010010000 $
b0010010001 %
1&
b10000001 +
b01101001 ,
#291
0&
#292
b010010010 #
b010010001 $
b0010010010 %
1&
b10000010 +
b01111001 ,
#293
0&
#294
b010010011 #
b010010010 $
b0010010011 %
1&
b01111010 +
b10000001 ,
#295
0&
#296
b010010100 #
b010010011 $
b0010010100 %
1&
b01101101 +
b10000010 ,
#297
0&
#298
b010010101 #
b010010100 $
b0010010101 %
1&
b01011101 +
b01111010 ,
#299
0&
#300
b010010110 #
b010010101 $
b0010010110 %
1&
b01011001 +
b01101101 ,
#301
0&
#302
b010010111 #
b010010110 $
b0010010111 %
1&
b01010111 +
b01011101 ,
#303
0&
#304
b010011000 #
b010010111 $
b0010011000 %
1&
b01100100 +
b01011001 ,
#305
0&
#306
b010011001 #
b010011000 $
b0010011001 %
1&
b01110000 +
b01010111 ,
#307
0&
#308
b010011010 #
b010011001 $
b0010011010 %
1&
b01111101 +
b01100100 ,
#309
0&
#310
b010011011 #
b010011010 $
b0010011011 %
1&
b10000010 +
b01110000 ,
#311
0&
#312
b010011100 #
b010011011 $
b0010011100 %
1&
b01111110 +
b01111101 ,
#313
0&
#314
b010011101 #
b010011100 $
b0010011101 %
1&
b01110001 +
b10000010 ,
#315
0&
#316
b010011110 #
b010011101 $
b0010011110 %
1&
b01100101 +
b01111110 ,
#317
0&
#318
b010011111 #
b010011110 $
b0010011111 %
1&
b01011011 +
b01110001 ,
#319
0&
#320
b010100000 #
b010011111 $
b0010100000 %
1&
b01011001 +
b01100101 ,
#321
0&
#322
b010100001 #
b010100000 $
b0010100001 %
1&
b01011111 +
b01011011 ,
#323
0&
#324
b010100010 #
b010100001 $
b0010100010 %
1&
b01101101 +
b01011001 ,
#325
0&
#326
b010100011 #
b010100010 $
b0010100011 %
1&
b01111001 +
b01011111 ,
#327
0&
#328
b010100100 #
b010100011 $
b0010100100 %
1&
b10000011 +
b01101101 ,
#329
0&
#330
b010100101 #
b010100100 $
b0010100101 %
1&
b10000100 +
b01111001 ,
#331
0&
#332
b010100110 #
b010100101 $
b0010100110 %
1&
b01101111 +
b10000011 ,
#333
0&
#334
b010100111 #
b010100110 $
b0010100111 %
1&
b01101101 +
b10000100 ,
#335
0&
#336
b010101000 #
b010100111 $
b0010101000 %
1&
b01101100 +
b01101111 ,
#337
0&
#338
b010101001 #
b010101000 $
b0010101001 %
1&
b01101011 +
b01101101 ,
#339
0&
#340
b010101010 #
b010101001 $
b0010101010 %
1&
b01101101 +
b01101100 ,
#341
0&
#342
b010101011 #
b010101010 $
b0010101011 %
1&
b01101110 +
b01101011 ,
#343
0&
#344
b010101100 #
b010101011 $
b0010101100 %
1&
b01101100 +
b01101101 ,
#345
0&
#346
b010101101 #
b010101100 $
b0010101101 %
1&
b01101101 +
b01101110 ,
#347
0&
#348
b010101110 #
b010101101 $
b0010101110 %
1&
b01101111 +
b01101100 ,
#349
0&
#350
b010101111 #
b010101110 $
b0010101111 %
1&
b01101100 +
b01101101 ,
#351
0&
#352
b010110000 #
b010101111 $
b0010110000 %
1&
b01101101 +
b01101111 ,
#353
0&
#354
b010110001 #
b010110000 $
b0010110001 %
1&
b01101110 +
b01101100 ,
#355
0&
#356
b010110010 #
b010110001 $
b0010110010 %
1&
b01101101 ,
#357
0&
#358
b010110011 #
b010110010 $
b0010110011 %
1&
b01101101 +
b01101110 ,
#359
0&
#360
b010110100 #
b010110011 $
b0010110100 %
1&
b01101110 +
#361
0&
#362
b010110101 #
b010110100 $
b0010110101 %
1&
b01101100 +
b01101101 ,
#363
0&
#364
b010110110 #
b010110101 $
b0010110110 %
1&
b01101101 +
b01101110 ,
#365
0&
#366
b010110111 #
b010110110 $
b0010110111 %
1&
b01101011 +
b01101100 ,
#367
0&
#368
b010111000 #
b010110111 $
b0010111000 %
1&
b01101101 ,
#369
0&
#370
b010111001 #
b010111000 $
b0010111001 %
1&
b01101101 +
b01101011 ,
#371
0&
#372
b010111010 #
b010111001 $
b0010111010 %
1&
b01101100 +
#373
0&
#374
b010111011 #
b010111010 $
b0010111011 %
1&
b01101110 +
b01101101 ,
#375
0&
#376
b010111100 #
b010111011 $
b0010111100 %
1&
b01101011 +
b01101100 ,
#377
0&
#378
b010111101 #
b010111100 $
b0010111101 %
1&
b01101110 ,
#379
0&
#380
b010111110 #
b010111101 $
b0010111110 %
1&
b01101110 +
b01101011 ,
#381
0&
#382
b010111111 #
b010111110 $
b0010111111 %
1&
b01101011 +
#383
0&
#384
b011000000 #
b010111111 $
b0011000000 %
1&
b01101100 +
b01101110 ,
#385
0&
#386
b011000001 #
b011000000 $
b0011000001 %
1&
b01101110 +
b01101011 ,
#387
0&
#388
b011000010 #
b011000001 $
b0011000010 %
1&
b01101111 +
b01101100 ,
#389
0&
#390
b011000011 #
b011000010 $
b0011000011 %
1&
b01101110 +
b01101110 ,
#391
0&
#392
b011000100 #
b011000011 $
b0011000100 %
1&
b01101111 ,
#393
0&
#394
b011000101 #
b011000100 $
b0011000101 %
1&
b01101101 +
b01101110 ,
#395
0&
#396
b011000110 #
b011000101 $
b0011000110 %
1&
b01101100 +
#397
0&
#398
b011000111 #
b011000110 $
b0011000111 %
1&
b01101101 +
b01101101 ,
#399
0&
#400
b011001000 #
b011000111 $
b0011001000 %
1&
b01101100 ,
#401
0&
#402
b011001001 #
b011001000 $
b0011001001 %
1&
b01101101 ,
#403
0&
#404
b011001010 #
b011001001 $
b0011001010 %
1&
b01101110 +
#405
0&
#406
b011001011 #
b011001010 $
b0011001011 %
1&
b01101100 +
#407
0&
#408
b011001100 #
b011001011 $
b0011001100 %
1&
b01101011 +
b01101110 ,
#409
0&
#410
b011001101 #
b011001100 $
b0011001101 %
1&
b01101110 +
b01101100 ,
#411
0&
#412
b011001110 #
b011001101 $
b0011001110 %
1&
b01101100 +
b01101011 ,
#413
0&
#414
b011001111 #
b011001110 $
b0011001111 %
1&
b01101110 +
b01101110 ,
#415
0&
#416
b011010000 #
b011001111 $
b0011010000 %
1&
b01101100 +
b01101100 ,
#417
0&
#418
b011010001 #
b011010000 $
b0011010001 %
1&
b01101110 ,
#419
0&
#420
b011010010 #
b011010001 $
b0011010010 %
1&
b01101110 +
b01101100 ,
#421
0&
#422
b011010011 #
b011010010 $
b0011010011 %
1&
b01101100 +
#423
0&
#424
b011010100 #
b011010011 $
b0011010100 %
1&
b01101011 +
b01101110 ,
#425
0&
#426
b011010101 #
b011010100 $
b0011010101 %
1&
b01101101 +
b01101100 ,
#427
0&
#428
b011010110 #
b011010101 $
b0011010110 %
1&
b01101011 ,
#429
0&
#430
b011010111 #
b011010110 $
b0011010111 %
1&
b01101101 ,
#431
0&
#432
b011011000 #
b011010111 $
b0011011000 %
1&
b01101111 +
#433
0&
#434
b011011001 #
b011011000 $
b0011011001 %
1&
b01101010 +
#435
0&
#436
b011011010 #
b011011001 $
b0011011010 %
1&
b01101111 ,
#437
0&
#438
b011011011 #
b011011010 $
b0011011011 %
1&
b01101111 +
b01101010 ,
#439
0&
#440
b011011100 #
b011011011 $
b0011011100 %
1&
#441
0&
#442
b011011101 #
b011011100 $
b0011011101 %
1&
b01101111 ,
#443
0&
#444
b011011110 #
b011011101 $
b0011011110 %
1&
b01110000 +
#445
0&
#446
b011011111 #
b011011110 $
b0011011111 %
1&
b01101111 +
#447
0&
#448
b011100000 #
b011011111 $
b0011100000 %
1&
b01110000 ,
#449
0&
#450
b011100001 #
b011100000 $
b0011100001 %
1&
b01110000 +
b01101111 ,
#451
0&
#452
b011100010 #
b011100001 $
b0011100010 %
1&
b01101110 +
#453
0&
#454
b011100011 #
b011100010 $
b0011100011 %
1&
b01101101 +
b01110000 ,
#455
0&
#456
b011100100 #
b011100011 $
b0011100100 %
1&
b01101100 +
b01101110 ,
#457
0&
#458
b011100101 #
b011100100 $
b0011100101 %
1&
b01101111 +
b01101101 ,
#459
0&
#460
b011100110 #
b011100101 $
b0011100110 %
1&
b01101110 +
b01101100 ,
#461
0&
#462
b011100111 #
b011100110 $
b0011100111 %
1&
b01101111 +
b01101111 ,
#463
0&
#464
b011101000 #
b011100111 $
b0011101000 %
1&
b01101110 +
b01101110 ,
#465
0&
#466
b011101001 #
b011101000 $
b0011101001 %
1&
b01101011 +
b01101111 ,
#467
0&
#468
b011101010 #
b011101001 $
b0011101010 %
1&
b01101101 +
b01101110 ,
#469
0&
#470
b011101011 #
b011101010 $
b0011101011 %
1&
b01101011 ,
#471
0&
#472
b011101100 #
b011101011 $
b0011101100 %
1&
b01101111 +
b01101101 ,
#473
0&
#474
b011101101 #
b011101100 $
b0011101101 %
1&
b01101100 +
#475
0&
#476
b011101110 #
b011101101 $
b0011101110 %
1&
b01101111 ,
#477
0&
#478
b011101111 #
b011101110 $
b0011101111 %
1&
b01101101 +
b01101100 ,
#479
0&
#480
b011110000 #
b011101111 $
b0011110000 %
1&
b01110000 +
#481
0&
#482
b011110001 #
b011110000 $
b0011110001 %
1&
b01101110 +
b01101101 ,
#483
0&
#484
b011110010 #
b011110001 $
b0011110010 %
1&
b01101100 +
b01110000 ,
#485
0&
#486
b011110011 #
b011110010 $
b0011110011 %
1&
b01101010 +
b01101110 ,
#487
0&
#488
b011110100 #
b011110011 $
b0011110100 %
1&
b01101011 +
b01101100 ,
#489
0&
#490
b011110101 #
b011110100 $
b0011110101 %
1&
b01101110 +
b01101010 ,
#491
0&
#492
b011110110 #
b011110101 $
b0011110110 %
1&
b01101111 +
b01101011 ,
#493
0&
#494
b011110111 #
b011110110 $
b0011110111 %
1&
b01101010 +
b01101110 ,
#495
0&
#496
b011111000 #
b011110111 $
b0011111000 %
1&
b01101100 +
b01101111 ,
#497
0&
#498
b011111001 #
b011111000 $
b0011111001 %
1&
b01101101 +
b01101010 ,
#499
0&
#500
b011111010 #
b011111001 $
b0011111010 %
1&
b01101111 +
b01101100 ,
#501
0&
#502
b011111011 #
b011111010 $
b0011111011 %
1&
b01101100 +
b01101101 ,
#503
0&
#504
b011111100 #
b011111011 $
b0011111100 %
1&
b01101011 +
b01101111 ,
#505
0&
#506
b011111101 #
b011111100 $
b0011111101 %
1&
b01101100 ,
#507
0&
#508
b011111110 #
b011111101 $
b0011111110 %
1&
b01101100 +
b01101011 ,
#509
0&
#510
b011111111 #
b011111110 $
b0011111111 %
1&
b01101001 +
#511
0&
#512
b100000000 #
b011111111 $
b0100000000 %
1&
b01101011 +
b01101100 ,
#513
0&
#514
b100000001 #
b100000000 $
b0100000001 %
1&
b01101001 +
b01101001 ,
#515
0&
#516
b100000010 #
b100000001 $
b0100000010 %
1&
b01101011 +
b01101011 ,
#517
0&
#518
b100000011 #
b100000010 $
b0100000011 %
1&
b01101001 ,
#519
0&
#520
b100000100 #
b100000011 $
b0100000100 %
1&
b01101100 +
b01101011 ,
#521
0&
#522
b100000101 #
b100000100 $
b0100000101 %
1&
#523
0&
#524
b100000110 #
b100000101 $
b0100000110 %
1&
b01101100 ,
#525
0&
#526
b100000111 #
b100000110 $
b0100000111 %
1&
b01101010 +
#527
0&
#528
b100001000 #
b100000111 $
b0100001000 %
1&
b01101101 +
#529
0&
#530
b100001001 #
b100001000 $
b0100001001 %
1&
b01101100 +
b01101010 ,
#531
0&
#532
b100001010 #
b100001001 $
b0100001010 %
1&
b01101011 +
b01101101 ,
#533
0&
#534
b100001011 #
b100001010 $
b0100001011 %
1&
b01101001 +
b01101100 ,
#535
0&
#536
b100001100 #
b100001011 $
b0100001100 %
1&
b01101011 ,
#537
0&
#538
b100001101 #
b100001100 $
b0100001101 %
1&
b01101010 +
b01101001 ,
#539
0&
#540
b100001110 #
b100001101 $
b0100001110 %
1&
b01101100 +
#541
0&
#542
b100001111 #
b100001110 $
b0100001111 %
1&
b01101101 +
b01101010 ,
#543
0&
#544
b100010000 #
b100001111 $
b0100010000 %
1&
b01101100 +
b01101100 ,
#545
0&
#546
b100010001 #
b100010000 $
b0100010001 %
1&
b01101011 +
b01101101 ,
#547
0&
#548
b100010010 #
b100010001 $
b0100010010 %
1&
b01101010 +
b01101100 ,
#549
0&
#550
b100010011 #
b100010010 $
b0100010011 %
1&
b01101001 +
b01101011 ,
#551
0&
#552
b100010100 #
b100010011 $
b0100010100 %
1&
b01101011 +
b01101010 ,
#553
0&
#554
b100010101 #
b100010100 $
b0100010101 %
1&
b01101100 +
b01101001 ,
